{
	"animations": [
		{
			"offsets": [
				0,
				0
			],
			"loop": false,
			"fps": 24,
			"anim": "idle",
			"indices": [],
			"name": "Idle"
		},
		{
			"offsets": [
				-3,
				-37
			],
			"loop": false,
			"fps": 24,
			"anim": "singDOWN",
			"indices": [],
			"name": "Down"
		},
		{
			"offsets": [
				34,
				65
			],
			"loop": false,
			"fps": 24,
			"anim": "singUP",
			"indices": [],
			"name": "Up"
		},
		{
			"offsets": [
				60,
				39
			],
			"loop": false,
			"fps": 24,
			"anim": "singLEFT",
			"indices": [],
			"name": "Right"
		},
		{
			"offsets": [
			    -62,
				26
			],
			"loop": false,
			"fps": 24,
			"anim": "singRIGHT",
			"indices": [],
			"name": "Left"
		}
	],
	"no_antialiasing": false,
	"image": "characters/niles",
	"position": [
		120,
		440
	],
	"healthicon": "niles",
	"flip_x": false,
	"healthbar_colors": [
		241,
		241,
		241
	],
	"camera_position": [
		110,
		0
	],
	"sing_duration": 6.1,
	"scale": 0.8
}